UART/fifo.sv
module fifo #(
    parameter DATA_WIDTH = 8,
    parameter ADDR_WIDTH = 4
)(
    input wire clk, reset,
    input wire rd, wr,
    input wire [DATA_WIDTH-1:0] w_data,
    output wire empty, full,
    output wire [DATA_WIDTH-1:0] r_data
);

    localparam DEPTH = 1 << ADDR_WIDTH;

    reg [DATA_WIDTH-1:0] array_reg [0:DEPTH-1];
    reg [ADDR_WIDTH-1:0] w_ptr_reg, w_ptr_next;
    reg [ADDR_WIDTH-1:0] r_ptr_reg, r_ptr_next;
    reg full_reg, empty_reg, full_next, empty_next;

    wire wr_en;

    // Escritura sincrónica
    always @(posedge clk) begin
        if (wr_en)
            array_reg[w_ptr_reg] <= w_data;
    end

    // Registros de estado
    always @(posedge clk or posedge reset) begin
        if (reset) begin
            w_ptr_reg <= 0;
            r_ptr_reg <= 0;
            full_reg <= 1'b0;
            empty_reg <= 1'b1;
        end else begin
            w_ptr_reg <= w_ptr_next;
            r_ptr_reg <= r_ptr_next;
            full_reg <= full_next;
            empty_reg <= empty_next;
        end
    end

    // Lógica de estado siguiente
    always @(*) begin
        w_ptr_next = w_ptr_reg;
        r_ptr_next = r_ptr_reg;
        full_next = full_reg;
        empty_next = empty_reg;

        case ({wr, rd})
            2'b01: // Lectura
                if (~empty_reg) begin
                    r_ptr_next = r_ptr_reg + 1;
                    full_next = 1'b0;
                    if (r_ptr_next == w_ptr_reg)
                        empty_next = 1'b1;
                end

            2'b10: // Escritura
                if (~full_reg) begin
                    w_ptr_next = w_ptr_reg + 1;
                    empty_next = 1'b0;
                    if (w_ptr_next == r_ptr_reg)
                        full_next = 1'b1;
                end

            2'b11: // Lectura y escritura simultánea
                begin
                    w_ptr_next = w_ptr_reg + 1;
                    r_ptr_next = r_ptr_reg + 1;
                end
        endcase
    end

    assign wr_en = wr & ~full_reg;
    assign r_data = array_reg[r_ptr_reg];
    assign full = full_reg;
    assign empty = empty_reg;

endmodule

UART/uart_tx.sv
module uart_tx #(
    parameter DBIT = 8,        // Bits de datos
    parameter SB_TICK = 16     // Ticks para stop bits
)(
    input wire clk, reset,
    input wire tx_start,       // Señal de inicio de transmisión
    input wire s_tick,         // Tick de baud rate
    input wire [7:0] din,      // Dato a transmitir
    output reg tx_done_tick,   // Pulso de transmisión completada
    output wire tx             // Línea de transmisión serial
);

    // Estados
    localparam [1:0]
        IDLE  = 2'b00,
        START = 2'b01,
        DATA  = 2'b10,
        STOP  = 2'b11;

    reg [1:0] state_reg, state_next;
    reg [3:0] s_reg, s_next;        // Contador de ticks
    reg [2:0] n_reg, n_next;        // Contador de bits
    reg [7:0] b_reg, b_next;        // Registro de desplazamiento
    reg tx_reg, tx_next;

    // Registro de estado
    always @(posedge clk or posedge reset) begin
        if (reset) begin
            state_reg <= IDLE;
            s_reg <= 0;
            n_reg <= 0;
            b_reg <= 0;
            tx_reg <= 1'b1;
        end else begin
            state_reg <= state_next;
            s_reg <= s_next;
            n_reg <= n_next;
            b_reg <= b_next;
            tx_reg <= tx_next;
        end
    end

    // Lógica de estado siguiente
    always @(*) begin
        state_next = state_reg;
        s_next = s_reg;
        n_next = n_reg;
        b_next = b_reg;
        tx_next = tx_reg;
        tx_done_tick = 1'b0;

        case (state_reg)
            IDLE: begin
                tx_next = 1'b1;
                if (tx_start) begin
                    state_next = START;
                    s_next = 0;
                    b_next = din;
                end
            end

            START: begin
                tx_next = 1'b0;  // Start bit
                if (s_tick) begin
                    if (s_reg == 15) begin
                        state_next = DATA;
                        s_next = 0;
                        n_next = 0;
                    end else begin
                        s_next = s_reg + 1;
                    end
                end
            end

            DATA: begin
                tx_next = b_reg[0];  // Bit LSB primero
                if (s_tick) begin
                    if (s_reg == 15) begin
                        s_next = 0;
                        b_next = {1'b0, b_reg[7:1]};  // Desplazar hacia la derecha
                        if (n_reg == (DBIT - 1)) begin
                            state_next = STOP;
                        end else begin
                            n_next = n_reg + 1;
                        end
                    end else begin
                        s_next = s_reg + 1;
                    end
                end
            end

            STOP: begin
                tx_next = 1'b1;  // Stop bit
                if (s_tick) begin
                    if (s_reg == (SB_TICK - 1)) begin
                        state_next = IDLE;
                        tx_done_tick = 1'b1;
                    end else begin
                        s_next = s_reg + 1;
                    end
                end
            end
        endcase
    end

    assign tx = tx_reg;

endmodule

UART/uart_rx.sv
module uart_rx #(
    parameter DBIT = 8,        // Bits de datos
    parameter SB_TICK = 16     // Ticks para stop bits
)(
    input wire clk, reset,
    input wire rx,             // Línea de recepción serial
    input wire s_tick,         // Tick de muestreo
    output reg rx_done_tick,   // Pulso de dato recibido
    output wire [7:0] dout     // Dato recibido
);

    // Estados
    localparam [1:0]
        IDLE  = 2'b00,
        START = 2'b01,
        DATA  = 2'b10,
        STOP  = 2'b11;

    reg [1:0] state_reg, state_next;
    reg [3:0] s_reg, s_next;        // Contador de ticks
    reg [2:0] n_reg, n_next;        // Contador de bits
    reg [7:0] b_reg, b_next;        // Registro de desplazamiento

    // Registro de estado
    always @(posedge clk or posedge reset) begin
        if (reset) begin
            state_reg <= IDLE;
            s_reg <= 0;
            n_reg <= 0;
            b_reg <= 0;
        end else begin
            state_reg <= state_next;
            s_reg <= s_next;
            n_reg <= n_next;
            b_reg <= b_next;
        end
    end

    // Lógica de estado siguiente
    always @(*) begin
        state_next = state_reg;
        s_next = s_reg;
        n_next = n_reg;
        b_next = b_reg;
        rx_done_tick = 1'b0;

        case (state_reg)
            IDLE:
                if (~rx) begin  // Detectar flanco de bajada (start bit)
                    state_next = START;
                    s_next = 0;
                end

            START:
                if (s_tick) begin
                    if (s_reg == 7) begin  // Muestrear en el medio del bit
                        state_next = DATA;
                        s_next = 0;
                        n_next = 0;
                    end else begin
                        s_next = s_reg + 1;
                    end
                end

            DATA:
                if (s_tick) begin
                    if (s_reg == 15) begin
                        s_next = 0;
                        b_next = {rx, b_reg[7:1]};  // Desplazar hacia la derecha
                        if (n_reg == (DBIT - 1)) begin
                            state_next = STOP;
                        end else begin
                            n_next = n_reg + 1;
                        end
                    end else begin
                        s_next = s_reg + 1;
                    end
                end

            STOP:
                if (s_tick) begin
                    if (s_reg == (SB_TICK - 1)) begin
                        state_next = IDLE;
                        rx_done_tick = 1'b1;
                    end else begin
                        s_next = s_reg + 1;
                    end
                end
        endcase
    end

    assign dout = b_reg;

endmodule

UART/baud_rate_generator.sv
module baud_rate_generator #(
    parameter M = 27  // Para 115200 baudios @ 50MHz: 50,000,000 / (16 * 115200) ≈ 27
)(
    input wire clk, reset,
    output wire tick
);

    reg [4:0] counter;

    always @(posedge clk or posedge reset) begin
        if (reset)
            counter <= 0;
        else if (counter == M-1)
            counter <= 0;
        else
            counter <= counter + 1;
    end

    assign tick = (counter == M-1);

endmodule

UART/uart.sv
module uart #(
    parameter DBIT = 8,        // Bits de datos
    parameter SB_TICK = 16,    // Ticks para stop bits
    parameter FIFO_W = 2       // Ancho de dirección FIFO (profundidad = 2^FIFO_W)
)(
    input wire clk, reset,
    // Interfaz UART
    input wire rx,
    output wire tx,
    // Interfaz de usuario
    input wire rd_uart, wr_uart,
    input wire [7:0] w_data,
    output wire [7:0] r_data,
    output wire tx_full, rx_empty
);

    // Señales internas
    wire tick;
    wire rx_done_tick, tx_done_tick;
    wire tx_empty;
    wire [7:0] tx_fifo_out, rx_data_out;
    wire tx_start;

    // Instancia del generador de baud rate
    baud_rate_generator brg (
        .clk(clk),
        .reset(reset),
        .tick(tick)
    );

    // Instancia del receptor UART
    uart_rx #(.DBIT(DBIT), .SB_TICK(SB_TICK)) uart_rx_inst (
        .clk(clk),
        .reset(reset),
        .rx(rx),
        .s_tick(tick),
        .rx_done_tick(rx_done_tick),
        .dout(rx_data_out)
    );

    // Instancia del transmisor UART
    uart_tx #(.DBIT(DBIT), .SB_TICK(SB_TICK)) uart_tx_inst (
        .clk(clk),
        .reset(reset),
        .tx_start(tx_start),
        .s_tick(tick),
        .din(tx_fifo_out),
        .tx_done_tick(tx_done_tick),
        .tx(tx)
    );

    // FIFO para recepción
    fifo #(.DATA_WIDTH(DBIT), .ADDR_WIDTH(FIFO_W)) fifo_rx (
        .clk(clk),
        .reset(reset),
        .rd(rd_uart),
        .wr(rx_done_tick),
        .w_data(rx_data_out),
        .empty(rx_empty),
        .full(),
        .r_data(r_data)
    );

    // FIFO para transmisión
    fifo #(.DATA_WIDTH(DBIT), .ADDR_WIDTH(FIFO_W)) fifo_tx (
        .clk(clk),
        .reset(reset),
        .rd(tx_done_tick),
        .wr(wr_uart),
        .w_data(w_data),
        .empty(tx_empty),
        .full(tx_full),
        .r_data(tx_fifo_out)
    );

    // Control de inicio de transmisión
    assign tx_start = ~tx_empty;

endmodule

UART/uart_tb.sv
module uart_tb;

    reg clk, reset;
    reg rx, rd_uart, wr_uart;
    reg [7:0] w_data;
    wire tx, tx_full, rx_empty;
    wire [7:0] r_data;

    // Instancia UART
    uart uut (
        .clk(clk),
        .reset(reset),
        .rx(rx),
        .tx(tx),
        .rd_uart(rd_uart),
        .wr_uart(wr_uart),
        .w_data(w_data),
        .r_data(r_data),
        .tx_full(tx_full),
        .rx_empty(rx_empty)
    );

    // Generador de reloj (50 MHz)
    always #10 clk = ~clk;

    // Tarea para enviar caracter por UART
    task send_byte;
        input [7:0] data;
        integer i;
        begin
            // Start bit
            rx = 1'b0;
            #8680;

            // Bits de datos (LSB first)
            for (i = 0; i < 8; i = i + 1) begin
                rx = data[i];
                #8680;
            end

            // Stop bit
            rx = 1'b1;
            #8680;
        end
    endtask

    // Tarea para enviar string - Versión Verilog
    task send_string;
        input [8*50:0] str;
        integer i;
        reg [7:0] char;
        begin
            $display(">> ENVIANDO: '%s'", str);
            for (i = 0; i < 50; i = i + 1) begin
                // Extraer caracter del string (big-endian)
                char = str >> ((49-i)*8);
                if (char != 8'h00) begin
                    send_byte(char);
                    #20000; // Pausa entre bytes
                end
            end
        end
    endtask

    // Tarea para transmitir dato
    task transmit_byte;
        input [7:0] data;
        begin
            wait(!tx_full);
            w_data = data;
            wr_uart = 1'b1;
            #40;
            wr_uart = 1'b0;
            #40;
        end
    endtask

    // Tarea para transmitir string - Versión Verilog
    task transmit_string;
        input [8*50:0] str;
        integer i;
        reg [7:0] char;
        begin
            $display("<< TRANSMITIENDO: '%s'", str);
            for (i = 0; i < 50; i = i + 1) begin
                // Extraer caracter del string (big-endian)
                char = str >> ((49-i)*8);
                if (char != 8'h00) begin
                    transmit_byte(char);
                    #5000; // Esperar entre bytes
                end
            end
        end
    endtask

    // Monitoreo automático de datos recibidos
    always @(posedge uut.rx_done_tick) begin
        #10; // Pequeño delay para estabilizar
        $display("✓ RECIBIDO: 0x%h ('%c')", uut.rx_data_out, uut.rx_data_out);
    end

    // Monitoreo de transmisiones completadas
    always @(posedge uut.tx_done_tick) begin
        $display("✓ TRANSMITIDO: Byte completado");
    end

    // Secuencia de prueba principal
    initial begin
        $dumpfile("uart.vcd");
        $dumpvars(0, uart_tb);
        
        // Inicialización
        clk = 1'b0;
        reset = 1'b1;
        rx = 1'b1;
        rd_uart = 1'b0;
        wr_uart = 1'b0;
        w_data = 8'h0;

        $display("========================================");
        $display("🚀 INICIANDO PRUEBAS UART");
        $display("========================================");

        // Reset
        #100 reset = 1'b0;
        #1000;

        // Prueba 1: Recepción de string simple
        $display("\n--- PRUEBA 1: Recepción ---");
        send_string("HOLA");
        #100000;

        // Leer datos recibidos
        $display("\n--- Leyendo FIFO RX ---");
        while (!rx_empty) begin
            rd_uart = 1'b1;
            #40;
            $display("📥 LEIDO: 0x%h ('%c')", r_data, r_data);
            rd_uart = 1'b0;
            #40;
        end

        #20000;

        // Prueba 2: Transmisión simple
        $display("\n--- PRUEBA 2: Transmisión ---");
        transmit_string("TEST");
        #100000;

        #20000;

        // Prueba 3: Caracteres individuales
        $display("\n--- PRUEBA 3: Caracteres individuales ---");
        send_byte("A");
        send_byte("B"); 
        send_byte("C");
        #50000;

        $display("\n--- Leyendo caracteres ---");
        while (!rx_empty) begin
            rd_uart = 1'b1;
            #40;
            $display("📥 LEIDO: 0x%h ('%c')", r_data, r_data);
            rd_uart = 1'b0;
            #40;
        end

        #20000;

        // Prueba 4: Números
        $display("\n--- PRUEBA 4: Números ---");
        send_string("123");
        #50000;

        $display("\n--- Leyendo números ---");
        while (!rx_empty) begin
            rd_uart = 1'b1;
            #40;
            $display("📥 LEIDO: 0x%h ('%c')", r_data, r_data);
            rd_uart = 1'b0;
            #40;
        end

        #20000;

        // Prueba final: String más largo
        $display("\n--- PRUEBA FINAL: String completo ---");
        send_string("UART OK!");
        #80000;

        $display("\n--- Datos finales ---");
        while (!rx_empty) begin
            rd_uart = 1'b1;
            #40;
            $display("📥 LEIDO: 0x%h ('%c')", r_data, r_data);
            rd_uart = 1'b0;
            #40;
        end

        $display("\n========================================");
        $display("✅ PRUEBAS COMPLETADAS");
        $display("========================================");
        #1000;
        $finish;
    end

endmodule

UART/uart.vcd
$date
	Tue Oct 28 18:47:53 2025
$end
$version
	Icarus Verilog
$end
$timescale
	1s
$end
$scope module uart_tb $end
$var wire 1 ! tx_full $end
$var wire 1 " tx $end
$var wire 1 # rx_empty $end
$var wire 8 $ r_data [7:0] $end
$var reg 1 % clk $end
$var reg 1 & rd_uart $end
$var reg 1 ' reset $end
$var reg 1 ( rx $end
$var reg 8 ) w_data [7:0] $end
$var reg 1 * wr_uart $end
$scope module uut $end
$var wire 1 % clk $end
$var wire 1 & rd_uart $end
$var wire 1 ' reset $end
$var wire 1 ( rx $end
$var wire 1 + tx_start $end
$var wire 8 , w_data [7:0] $end
$var wire 1 * wr_uart $end
$var wire 1 ! tx_full $end
$var wire 8 - tx_fifo_out [7:0] $end
$var wire 1 . tx_empty $end
$var wire 1 / tx_done_tick $end
$var wire 1 " tx $end
$var wire 1 0 tick $end
$var wire 1 # rx_empty $end
$var wire 1 1 rx_done_tick $end
$var wire 8 2 rx_data_out [7:0] $end
$var wire 8 3 r_data [7:0] $end
$scope module brg $end
$var wire 1 % clk $end
$var wire 1 ' reset $end
$var wire 1 0 tick $end
$var reg 5 4 counter [4:0] $end
$upscope $end
$scope module fifo_rx $end
$var wire 1 % clk $end
$var wire 1 # empty $end
$var wire 1 5 full $end
$var wire 8 6 r_data [7:0] $end
$var wire 1 & rd $end
$var wire 1 ' reset $end
$var wire 1 7 wr_en $end
$var wire 1 1 wr $end
$var wire 8 8 w_data [7:0] $end
$var reg 1 9 empty_next $end
$var reg 1 : empty_reg $end
$var reg 1 ; full_next $end
$var reg 1 < full_reg $end
$var reg 2 = r_ptr_next [1:0] $end
$var reg 2 > r_ptr_reg [1:0] $end
$var reg 2 ? w_ptr_next [1:0] $end
$var reg 2 @ w_ptr_reg [1:0] $end
$upscope $end
$scope module fifo_tx $end
$var wire 1 % clk $end
$var wire 1 ! full $end
$var wire 8 A r_data [7:0] $end
$var wire 1 ' reset $end
$var wire 8 B w_data [7:0] $end
$var wire 1 * wr $end
$var wire 1 C wr_en $end
$var wire 1 / rd $end
$var wire 1 . empty $end
$var reg 1 D empty_next $end
$var reg 1 . empty_reg $end
$var reg 1 E full_next $end
$var reg 1 F full_reg $end
$var reg 2 G r_ptr_next [1:0] $end
$var reg 2 H r_ptr_reg [1:0] $end
$var reg 2 I w_ptr_next [1:0] $end
$var reg 2 J w_ptr_reg [1:0] $end
$upscope $end
$scope module uart_rx_inst $end
$var wire 1 % clk $end
$var wire 8 K dout [7:0] $end
$var wire 1 ' reset $end
$var wire 1 ( rx $end
$var wire 1 0 s_tick $end
$var reg 8 L b_next [7:0] $end
$var reg 8 M b_reg [7:0] $end
$var reg 3 N n_next [2:0] $end
$var reg 3 O n_reg [2:0] $end
$var reg 1 1 rx_done_tick $end
$var reg 4 P s_next [3:0] $end
$var reg 4 Q s_reg [3:0] $end
$var reg 2 R state_next [1:0] $end
$var reg 2 S state_reg [1:0] $end
$upscope $end
$scope module uart_tx_inst $end
$var wire 1 % clk $end
$var wire 8 T din [7:0] $end
$var wire 1 ' reset $end
$var wire 1 0 s_tick $end
$var wire 1 " tx $end
$var wire 1 + tx_start $end
$var reg 8 U b_next [7:0] $end
$var reg 8 V b_reg [7:0] $end
$var reg 3 W n_next [2:0] $end
$var reg 3 X n_reg [2:0] $end
$var reg 4 Y s_next [3:0] $end
$var reg 4 Z s_reg [3:0] $end
$var reg 2 [ state_next [1:0] $end
$var reg 2 \ state_reg [1:0] $end
$var reg 1 / tx_done_tick $end
$var reg 1 ] tx_next $end
$var reg 1 ^ tx_reg $end
$upscope $end
$upscope $end
$scope task send_byte $end
$var reg 8 _ data [7:0] $end
$var integer 32 ` i [31:0] $end
$upscope $end
$scope task send_string $end
$var reg 8 a char [7:0] $end
$var reg 401 b str [400:0] $end
$var integer 32 c i [31:0] $end
$upscope $end
$scope task transmit_byte $end
$var reg 8 d data [7:0] $end
$upscope $end
$scope task transmit_string $end
$var reg 8 e char [7:0] $end
$var reg 401 f str [400:0] $end
$var integer 32 g i [31:0] $end
$upscope $end
$upscope $end
$enddefinitions $end
#0
$dumpvars
bx g
bx f
bx e
bx d
bx c
bx b
bx a
bx `
bx _
1^
1]
b0 \
b0 [
b0 Z
b0 Y
b0 X
b0 W
b0 V
b0 U
bx T
b0 S
b0 R
b0 Q
b0 P
b0 O
b0 N
b0 M
b0 L
b0 K
b0 J
b0 I
b0 H
b0 G
0F
0E
1D
0C
b0 B
bx A
b0 @
b0 ?
b0 >
b0 =
0<
0;
1:
19
b0 8
07
bx 6
05
b0 4
bx 3
b0 2
01
00
0/
1.
bx -
b0 ,
0+
0*
b0 )
1(
1'
0&
0%
bx $
1#
1"
0!
$end
#10
1%
#20
0%
#30
1%
#40
0%
#50
1%
#60
0%
#70
1%
#80
0%
#90
1%
#100
0%
0'
#110
b1 4
1%
#120
0%
#130
b10 4
1%
#140
0%
#150
b11 4
1%
#160
0%
#170
b100 4
1%
#180
0%
#190
b101 4
1%
#200
0%
#210
b110 4
1%
#220
0%
#230
b111 4
1%
#240
0%
#250
b1000 4
1%
#260
0%
#270
b1001 4
1%
#280
0%
#290
b1010 4
1%
#300
0%
#310
b1011 4
1%
#320
0%
#330
b1100 4
1%
#340
0%
#350
b1101 4
1%
#360
0%
#370
b1110 4
1%
#380
0%
#390
b1111 4
1%
#400
0%
#410
b10000 4
1%
#420
0%
#430
b10001 4
1%
#440
0%
#450
b10010 4
1%
#460
0%
#470
b10011 4
1%
#480
0%
#490
b10100 4
1%
#500
0%
#510
b10101 4
1%
#520
0%
#530
b10110 4
1%
#540
0%
#550
b10111 4
1%
#560
0%
#570
b11000 4
1%
#580
0%
#590
b11001 4
1%
#600
0%
#610
10
b11010 4
1%
#620
0%
#630
00
b0 4
1%
#640
0%
#650
b1 4
1%
#660
0%
#670
b10 4
1%
#680
0%
#690
b11 4
1%
#700
0%
#710
b100 4
1%
#720
0%
#730
b101 4
1%
#740
0%
#750
b110 4
1%
#760
0%
#770
b111 4
1%
#780
0%
#790
b1000 4
1%
#800
0%
#810
b1001 4
1%
#820
0%
#830
b1010 4
1%
#840
0%
#850
b1011 4
1%
#860
0%
#870
b1100 4
1%
#880
0%
#890
b1101 4
1%
#900
0%
#910
b1110 4
1%
#920
0%
#930
b1111 4
1%
#940
0%
#950
b10000 4
1%
#960
0%
#970
b10001 4
1%
#980
0%
#990
b10010 4
1%
#1000
0%
#1010
b10011 4
1%
#1020
0%
#1030
b10100 4
1%
#1040
0%
#1050
b10101 4
1%
#1060
0%
#1070
b10110 4
1%
#1080
0%
#1090
b10111 4
1%
#1100
b1 R
0%
0(
b1001000 _
b1001000 a
b101110 c
b1001000010011110100110001000001 b
#1110
b11000 4
b1 S
1%
#1120
0%
#1130
b11001 4
1%
#1140
0%
#1150
b1 P
10
b11010 4
1%
#1160
0%
#1170
b1 Q
00
b0 4
1%
#1180
0%
#1190
b1 4
1%
#1200
0%
#1210
b10 4
1%
#1220
0%
#1230
b11 4
1%
#1240
0%
#1250
b100 4
1%
#1260
0%
#1270
b101 4
1%
#1280
0%
#1290
b110 4
1%
#1300
0%
#1310
b111 4
1%
#1320
0%
#1330
b1000 4
1%
#1340
0%
#1350
b1001 4
1%
#1360
0%
#1370
b1010 4
1%
#1380
0%
#1390
b1011 4
1%
#1400
0%
#1410
b1100 4
1%
#1420
0%
#1430
b1101 4
1%
#1440
0%
#1450
b1110 4
1%
#1460
0%
#1470
b1111 4
1%
#1480
0%
#1490
b10000 4
1%
#1500
0%
#1510
b10001 4
1%
#1520
0%
#1530
b10010 4
1%
#1540
0%
#1550
b10011 4
1%
#1560
0%
#1570
b10100 4
1%
#1580
0%
#1590
b10101 4
1%
#1600
0%
#1610
b10110 4
1%
#1620
0%
#1630
b10111 4
1%
#1640
0%
#1650
b11000 4
1%
#1660
0%
#1670
b11001 4
1%
#1680
0%
#1690
b10 P
10
b11010 4
1%
#1700
0%
#1710
00
b0 4
b10 Q
1%
#1720
0%
#1730
b1 4
1%
#1740
0%
#1750
b10 4
1%
#1760
0%
#1770
b11 4
1%
#1780
0%
#1790
b100 4
1%
#1800
0%
#1810
b101 4
1%
#1820
0%
#1830
b110 4
1%
#1840
0%
#1850
b111 4
1%
#1860
0%
#1870
b1000 4
1%
#1880
0%
#1890
b1001 4
1%
#1900
0%
#1910
b1010 4
1%
#1920
0%
#1930
b1011 4
1%
#1940
0%
#1950
b1100 4
1%
#1960
0%
#1970
b1101 4
1%
#1980
0%
#1990
b1110 4
1%
#2000
0%
#2010
b1111 4
1%
#2020
0%
#2030
b10000 4
1%
#2040
0%
#2050
b10001 4
1%
#2060
0%
#2070
b10010 4
1%
#2080
0%
#2090
b10011 4
1%
#2100
0%
#2110
b10100 4
1%
#2120
0%
#2130
b10101 4
1%
#2140
0%
#2150
b10110 4
1%
#2160
0%
#2170
b10111 4
1%
#2180
0%
#2190
b11000 4
1%
#2200
0%
#2210
b11001 4
1%
#2220
0%
#2230
b11 P
10
b11010 4
1%
#2240
0%
#2250
b11 Q
00
b0 4
1%
#2260
0%
#2270
b1 4
1%
#2280
0%
#2290
b10 4
1%
#2300
0%
#2310
b11 4
1%
#2320
0%
#2330
b100 4
1%
#2340
0%
#2350
b101 4
1%
#2360
0%
#2370
b110 4
1%
#2380
0%
#2390
b111 4
1%
#2400
0%
#2410
b1000 4
1%
#2420
0%
#2430
b1001 4
1%
#2440
0%
#2450
b1010 4
1%
#2460
0%
#2470
b1011 4
1%
#2480
0%
#2490
b1100 4
1%
#2500
0%
#2510
b1101 4
1%
#2520
0%
#2530
b1110 4
1%
#2540
0%
#2550
b1111 4
1%
#2560
0%
#2570
b10000 4
1%
#2580
0%
#2590
b10001 4
1%
#2600
0%
#2610
b10010 4
1%
#2620
0%
#2630
b10011 4
1%
#2640
0%
#2650
b10100 4
1%
#2660
0%
#2670
b10101 4
1%
#2680
0%
#2690
b10110 4
1%
#2700
0%
#2710
b10111 4
1%
#2720
0%
#2730
b11000 4
1%
#2740
0%
#2750
b11001 4
1%
#2760
0%
#2770
b100 P
10
b11010 4
1%
#2780
0%
#2790
00
b0 4
b100 Q
1%
#2800
0%
#2810
b1 4
1%
#2820
0%
#2830
b10 4
1%
#2840
0%
#2850
b11 4
1%
#2860
0%
#2870
b100 4
1%
#2880
0%
#2890
b101 4
1%
#2900
0%
#2910
b110 4
1%
#2920
0%
#2930
b111 4
1%
#2940
0%
#2950
b1000 4
1%
#2960
0%
#2970
b1001 4
1%
#2980
0%
#2990
b1010 4
1%
#3000
0%
#3010
b1011 4
1%
#3020
0%
#3030
b1100 4
1%
#3040
0%
#3050
b1101 4
1%
#3060
0%
#3070
b1110 4
1%
#3080
0%
#3090
b1111 4
1%
#3100
0%
#3110
b10000 4
1%
#3120
0%
#3130
b10001 4
1%
#3140
0%
#3150
b10010 4
1%
#3160
0%
#3170
b10011 4
1%
#3180
0%
#3190
b10100 4
1%
#3200
0%
#3210
b10101 4
1%
#3220
0%
#3230
b10110 4
1%
#3240
0%
#3250
b10111 4
1%
#3260
0%
#3270
b11000 4
1%
#3280
0%
#3290
b11001 4
1%
#3300
0%
#3310
b101 P
10
b11010 4
1%
#3320
0%
#3330
b101 Q
00
b0 4
1%
#3340
0%
#3350
b1 4
1%
#3360
0%
#3370
b10 4
1%
#3380
0%
#3390
b11 4
1%
#3400
0%
#3410
b100 4
1%
#3420
0%
#3430
b101 4
1%
#3440
0%
#3450
b110 4
1%
#3460
0%
#3470
b111 4
1%
#3480
0%
#3490
b1000 4
1%
#3500
0%
#3510
b1001 4
1%
#3520
0%
#3530
b1010 4
1%
#3540
0%
#3550
b1011 4
1%
#3560
0%
#3570
b1100 4
1%
#3580
0%
#3590
b1101 4
1%
#3600
0%
#3610
b1110 4
1%
#3620
0%
#3630
b1111 4
1%
#3640
0%
#3650
b10000 4
1%
#3660
0%
#3670
b10001 4
1%
#3680
0%
#3690
b10010 4
1%
#3700
0%
#3710
b10011 4
1%
#3720
0%
#3730
b10100 4
1%
#3740
0%
#3750
b10101 4
1%
#3760
0%
#3770
b10110 4
1%
#3780
0%
#3790
b10111 4
1%
#3800
0%
#3810
b11000 4
1%
#3820
0%
#3830
b11001 4
1%
#3840
0%
#3850
b110 P
10
b11010 4
1%
#3860
0%
#3870
00
b0 4
b110 Q
1%
#3880
0%
#3890
b1 4
1%
#3900
0%
#3910
b10 4
1%
#3920
0%
#3930
b11 4
1%
#3940
0%
#3950
b100 4
1%
#3960
0%
#3970
b101 4
1%
#3980
0%
#3990
b110 4
1%
#4000
0%
#4010
b111 4
1%
#4020
0%
#4030
b1000 4
1%
#4040
0%
#4050
b1001 4
1%
#4060
0%
#4070
b1010 4
1%
#4080
0%
#4090
b1011 4
1%
#4100
0%
#4110
b1100 4
1%
#4120
0%
#4130
b1101 4
1%
#4140
0%
#4150
b1110 4
1%
#4160
0%
#4170
b1111 4
1%
#4180
0%
#4190
b10000 4
1%
#4200
0%
#4210
b10001 4
1%
#4220
0%
#4230
b10010 4
1%
#4240
0%
#4250
b10011 4
1%
#4260
0%
#4270
b10100 4
1%
#4280
0%
#4290
b10101 4
1%
#4300
0%
#4310
b10110 4
1%
#4320
0%
#4330
b10111 4
1%
#4340
0%
#4350
b11000 4
1%
#4360
0%
#4370
b11001 4
1%
#4380
0%
#4390
b111 P
10
b11010 4
1%
#4400
0%
#4410
b111 Q
00
b0 4
1%
#4420
0%
#4430
b1 4
1%
#4440
0%
#4450
b10 4
1%
#4460
0%
#4470
b11 4
1%
#4480
0%
#4490
b100 4
1%
#4500
0%
#4510
b101 4
1%
#4520
0%
#4530
b110 4
1%
#4540
0%
#4550
b111 4
1%
#4560
0%
#4570
b1000 4
1%
#4580
0%
#4590
b1001 4
1%
#4600
0%
#4610
b1010 4
1%
#4620
0%
#4630
b1011 4
1%
#4640
0%
#4650
b1100 4
1%
#4660
0%
#4670
b1101 4
1%
#4680
0%
#4690
b1110 4
1%
#4700
0%
#4710
b1111 4
1%
#4720
0%
#4730
b10000 4
1%
#4740
0%
#4750
b10001 4
1%
#4760
0%
#4770
b10010 4
1%
#4780
0%
#4790
b10011 4
1%
#4800
0%
#4810
b10100 4
1%
#4820
0%
#4830
b10101 4
1%
#4840
0%
#4850
b10110 4
1%
#4860
0%
#4870
b10111 4
1%
#4880
0%
#4890
b11000 4
1%
#4900
0%
#4910
b11001 4
1%
#4920
0%
#4930
b0 P
b10 R
10
b11010 4
1%
#4940
0%
#4950
00
b0 4
b0 Q
b10 S
1%
#4960
0%
#4970
b1 4
1%
#4980
0%
#4990
b10 4
1%
#5000
0%
#5010
b11 4
1%
#5020
0%
#5030
b100 4
1%
#5040
0%
#5050
b101 4
1%
#5060
0%
#5070
b110 4
1%
#5080
0%
#5090
b111 4
1%
#5100
0%
#5110
b1000 4
1%
#5120
0%
#5130
b1001 4
1%
#5140
0%
#5150
b1010 4
1%
#5160
0%
#5170
b1011 4
1%
#5180
0%
#5190
b1100 4
1%
#5200
0%
#5210
b1101 4
1%
#5220
0%
#5230
b1110 4
1%
#5240
0%
#5250
b1111 4
1%
#5260
0%
#5270
b10000 4
1%
#5280
0%
#5290
b10001 4
1%
#5300
0%
#5310
b10010 4
1%
#5320
0%
#5330
b10011 4
1%
#5340
0%
#5350
b10100 4
1%
#5360
0%
#5370
b10101 4
1%
#5380
0%
#5390
b10110 4
1%
#5400
0%
#5410
b10111 4
1%
#5420
0%
#5430
b11000 4
1%
#5440
0%
#5450
b11001 4
1%
#5460
0%
#5470
b1 P
10
b11010 4
1%
#5480
0%
#5490
b1 Q
00
b0 4
1%
#5500
0%
#5510
b1 4
1%
#5520
0%
#5530
b10 4
1%
#5540
0%
#5550
b11 4
1%
#5560
0%
#5570
b100 4
1%
#5580
0%
#5590
b101 4
1%
#5600
0%
#5610
b110 4
1%
#5620
0%
#5630
b111 4
1%
#5640
0%
#5650
b1000 4
1%
#5660
0%
#5670
b1001 4
1%
#5680
0%
#5690
b1010 4
1%
#5700
0%
#5710
b1011 4
1%
#5720
0%
#5730
b1100 4
1%
#5740
0%
#5750
b1101 4
1%
#5760
0%
#5770
b1110 4
1%
#5780
0%
#5790
b1111 4
1%
#5800
0%
#5810
b10000 4
1%
#5820
0%
#5830
b10001 4
1%
#5840
0%
#5850
b10010 4
1%
#5860
0%
#5870
b10011 4
1%
#5880
0%
#5890
b10100 4
1%
#5900
0%
#5910
b10101 4
1%
#5920
0%
#5930
b10110 4
1%
#5940
0%
#5950
b10111 4
1%
#5960
0%
#5970
b11000 4
1%
#5980
0%
#5990
b11001 4
1%
#6000
0%
#6010
b10 P
10
b11010 4
1%
#6020
0%
#6030
00
b0 4
b10 Q
1%
#6040
0%
#6050
b1 4
1%
#6060
0%
#6070
b10 4
1%
#6080
0%
#6090
b11 4
1%
#6100
0%
#6110
b100 4
1%
#6120
0%
